tkan/__init__.py
tkan/tkan.py
tkan-0.4.3.dist-info/METADATA
tkan-0.4.3.dist-info/WHEEL
tkan-0.4.3.dist-info/RECORD
